sacf/CMakeLists.txt
sacf/__init__.py
sacf/correlator.cpython-37m-darwin.so
sacf/datastructure.cpython-37m-darwin.so
sacf/sacf.py
sacf/correlator/Correlator.cpp
sacf/correlator/correlator_bindings.cpp
sacf/datastructure/DataStructure.cpp
sacf/datastructure/datastructure_bindings.cpp
sacf/include/Correlator.h
sacf/include/DataStructure.h
sacf/include/pybind11/CMakeLists.txt
sacf/include/pybind11/include/pybind11/attr.h
sacf/include/pybind11/include/pybind11/buffer_info.h
sacf/include/pybind11/include/pybind11/cast.h
sacf/include/pybind11/include/pybind11/chrono.h
sacf/include/pybind11/include/pybind11/common.h
sacf/include/pybind11/include/pybind11/complex.h
sacf/include/pybind11/include/pybind11/eigen.h
sacf/include/pybind11/include/pybind11/embed.h
sacf/include/pybind11/include/pybind11/eval.h
sacf/include/pybind11/include/pybind11/functional.h
sacf/include/pybind11/include/pybind11/iostream.h
sacf/include/pybind11/include/pybind11/numpy.h
sacf/include/pybind11/include/pybind11/operators.h
sacf/include/pybind11/include/pybind11/options.h
sacf/include/pybind11/include/pybind11/pybind11.h
sacf/include/pybind11/include/pybind11/pytypes.h
sacf/include/pybind11/include/pybind11/stl.h
sacf/include/pybind11/include/pybind11/stl_bind.h
sacf/include/pybind11/include/pybind11/detail/class.h
sacf/include/pybind11/include/pybind11/detail/common.h
sacf/include/pybind11/include/pybind11/detail/descr.h
sacf/include/pybind11/include/pybind11/detail/init.h
sacf/include/pybind11/include/pybind11/detail/internals.h
sacf/include/pybind11/include/pybind11/detail/typeid.h
sacf/include/pybind11/tests/CMakeLists.txt
sacf/include/pybind11/tests/constructor_stats.h
sacf/include/pybind11/tests/local_bindings.h
sacf/include/pybind11/tests/object.h
sacf/include/pybind11/tests/pybind11_cross_module_tests.cpp
sacf/include/pybind11/tests/pybind11_tests.cpp
sacf/include/pybind11/tests/pybind11_tests.h
sacf/include/pybind11/tests/test_buffers.cpp
sacf/include/pybind11/tests/test_builtin_casters.cpp
sacf-2.0.dist-info/LICENSE
sacf-2.0.dist-info/METADATA
sacf-2.0.dist-info/WHEEL
sacf-2.0.dist-info/top_level.txt
sacf-2.0.dist-info/RECORD
