Metadata-Version: 2.1
Name: sacf
Version: 2.0
Summary: A selective estimator of the autocorrelation function for non-uniformly sampled timeseries data
Author: Joshua Briegal
Author-email: "Joshua T. Briegal" <jtb34@cam.ac.uk>
Project-URL: Homepage, https://github.com/joshbriegal/sacf
Project-URL: Bug Tracker, https://github.com/joshbriegal/sacf/issues
Classifier: Programming Language :: Python :: 3
Classifier: License :: OSI Approved :: MIT License
Classifier: Operating System :: OS Independent
Requires-Python: >=3.7
License-File: LICENSE
